<keymap version="1" name="zengyan" parent="Mac OS X 10.5+">
  <action id="$EditorTranslateAction">
    <keyboard-shortcut first-keystroke="ctrl meta u" />
    <keyboard-shortcut first-keystroke="meta i" />
  </action>
  <action id="ActivateTerminalToolWindow">
    <keyboard-shortcut first-keystroke="alt f12" />
    <keyboard-shortcut first-keystroke="shift t" />
  </action>
  <action id="CopyElement" />
  <action id="ECTranslation">
    <keyboard-shortcut first-keystroke="meta i" />
  </action>
  <action id="Editor EditorTranslateAction">
    <keyboard-shortcut first-keystroke="meta i" />
  </action>
  <action id="FixDocComment">
    <keyboard-shortcut first-keystroke="alt slash" />
  </action>
  <action id="ForceStepInto" />
  <action id="ForceStepOver" />
  <action id="HippieCompletion" />
  <action id="Move" />
  <action id="NextDiff" />
  <action id="Resume">
    <keyboard-shortcut first-keystroke="meta alt r" />
    <keyboard-shortcut first-keystroke="f5" />
  </action>
  <action id="SmartStepInto" />
  <action id="StepInto">
    <keyboard-shortcut first-keystroke="f6" />
  </action>
  <action id="StepOut">
    <keyboard-shortcut first-keystroke="f8" />
  </action>
  <action id="StepOver">
    <keyboard-shortcut first-keystroke="f7" />
  </action>
  <action id="android.deploy.ApplyChanges">
    <keyboard-shortcut first-keystroke="ctrl meta r" />
  </action>
  <action id="android.deploy.CodeSwap">
    <keyboard-shortcut first-keystroke="shift ctrl meta r" />
  </action>
</keymap>